{
  "generated_at": "2026-06-24T06:26:38Z",
  "items": [
    {
      "source": "media",
      "id": "us7000sv6e",
      "ts": "2026-06-22T10:22:23Z",
      "type": "quake",
      "severity": "info",
      "title": "42 km SSW of Jurm, Afghanistan",
      "body": "42 km SSW of Jurm, Afghanistan",
      "mag": 5.2,
      "lat": 36.4903,
      "lon": 70.733,
      "links": [
        "https://earthquake.usgs.gov/earthquakes/eventpage/us7000sv6e"
      ]
    },
    {
      "source": "media",
      "id": "us6000t7gf",
      "ts": "2026-06-22T19:46:11Z",
      "type": "quake",
      "severity": "info",
      "title": "Kermadec Islands region",
      "body": "Kermadec Islands region",
      "mag": 5.1,
      "lat": -31.9328,
      "lon": -178.2858,
      "links": [
        "https://earthquake.usgs.gov/earthquakes/eventpage/us6000t7gf"
      ]
    },
    {
      "source": "media",
      "id": "us6000t7it",
      "ts": "2026-06-23T01:56:49Z",
      "type": "quake",
      "severity": "info",
      "title": "186 km N of Fais, Micronesia",
      "body": "186 km N of Fais, Micronesia",
      "mag": 5.1,
      "lat": 11.4493,
      "lon": 140.6086,
      "links": [
        "https://earthquake.usgs.gov/earthquakes/eventpage/us6000t7it"
      ]
    },
    {
      "source": "media",
      "id": "us6000t7iy",
      "ts": "2026-06-23T02:26:20Z",
      "type": "quake",
      "severity": "info",
      "title": "Kermadec Islands region",
      "body": "Kermadec Islands region",
      "mag": 5.3,
      "lat": -27.1921,
      "lon": -177.7691,
      "links": [
        "https://earthquake.usgs.gov/earthquakes/eventpage/us6000t7iy"
      ]
    },
    {
      "source": "media",
      "id": "us6000t7k4",
      "ts": "2026-06-23T07:11:14Z",
      "type": "quake",
      "severity": "info",
      "title": "174 km E of Hihifo, Tonga",
      "body": "174 km E of Hihifo, Tonga",
      "mag": 5,
      "lat": -16.1772,
      "lon": -172.1796,
      "links": [
        "https://earthquake.usgs.gov/earthquakes/eventpage/us6000t7k4"
      ]
    },
    {
      "source": "media",
      "id": "us6000t7lb",
      "ts": "2026-06-23T13:58:34Z",
      "type": "quake",
      "severity": "info",
      "title": "120 km S of Isangel, Vanuatu",
      "body": "120 km S of Isangel, Vanuatu",
      "mag": 5.3,
      "lat": -20.6302,
      "lon": 169.2307,
      "links": [
        "https://earthquake.usgs.gov/earthquakes/eventpage/us6000t7lb"
      ]
    },
    {
      "source": "media",
      "id": "us6000t7ll",
      "ts": "2026-06-23T15:29:02Z",
      "type": "quake",
      "severity": "info",
      "title": "265 km SSE of Dunhuang, China",
      "body": "265 km SSE of Dunhuang, China",
      "mag": 5.2,
      "lat": 37.8214,
      "lon": 95.2983,
      "links": [
        "https://earthquake.usgs.gov/earthquakes/eventpage/us6000t7ll"
      ]
    },
    {
      "source": "media",
      "id": "us6000t7rx",
      "ts": "2026-06-24T02:04:49Z",
      "type": "quake",
      "severity": "info",
      "title": "71 km WNW of Catuday, Philippines",
      "body": "71 km WNW of Catuday, Philippines",
      "mag": 5,
      "lat": 16.5122,
      "lon": 119.1731,
      "links": [
        "https://earthquake.usgs.gov/earthquakes/eventpage/us6000t7rx"
      ]
    }
  ]
}