{"timestamp_utc":"2025-10-09T11:15:54Z","sci":["Kp 2.0","Solar wind ~387 km/s","Bz +9.1 nT","Max flare 24h: C1.7"],"mystical":["Field is fairly steady today.","Light movement, water, and brief outdoor time support balance."],"care":["Easy movement + hydration"],"today":{"kp":2.0,"sw_kms":387,"bz_nt":9.1,"flare_24h":"C1.7","cme_headline":"Moderate CMEs in last 72h"},"schumann":{"combined":{"f1_hz":8.44,"primary":"tomsk","delta_hz":1.2},"sources":{"cumiana":{"f1_hz":7.6,"image":"https://gennwu.github.io/gaiaeyes-media/images/cumiana_latest.png"},"tomsk":{"f1_hz":8.8,"image":"https://gennwu.github.io/gaiaeyes-media/images/tomsk_latest.png"}}}}