{"timestamp_utc":"2026-05-13T06:31:45Z","items":[{"title":"America’s Emerald Isle","link":"https://science.nasa.gov/earth/earth-observatory/americas-emerald-isle/","published_at":"2026-05-13T04:00:00Z","source":"NASA Breaking","category":"space_activity"},{"title":"NASA Langley Engineer Attends FAA Training","link":"https://www.nasa.gov/general/nasa-langley-engineer-attends-faa-training/","published_at":"2026-05-12T18:57:31Z","source":"NASA Breaking","category":"space_activity"},{"title":"Perseverance Stuns in New Selfie","link":"https://www.nasa.gov/image-article/perseverance-stuns-in-new-selfie/","published_at":"2026-05-12T17:22:51Z","source":"NASA Breaking","category":"space_activity"},{"title":"NASA’s Perseverance Rover Snaps Selfie in Mars’ Western Frontier","link":"https://www.nasa.gov/missions/mars-2020-perseverance/perseverance-rover/nasas-perseverance-rover-snaps-selfie-in-mars-western-frontier/","published_at":"2026-05-12T16:48:31Z","source":"NASA Breaking","category":"space_activity"},{"title":"NASA’s Perseverance Captures Panorama at ‘Arbot’","link":"https://science.nasa.gov/photojournal/nasas-perseverance-captures-panorama-at-arbot/","published_at":"2026-05-12T16:46:56Z","source":"NASA Breaking","category":"space_activity"},{"title":"NASA’s Perseverance Rover Snaps Westernmost Selfie","link":"https://science.nasa.gov/photojournal/nasas-perseverance-rover-snaps-westernmost-selfie/","published_at":"2026-05-12T16:45:58Z","source":"NASA Breaking","category":"space_activity"},{"title":"Hello Universe: NASA’s Next-Gen Space Processor Undergoes Testing","link":"https://www.nasa.gov/technology/hello-universe-nasas-next-gen-space-processor-undergoes-testing/","published_at":"2026-05-12T15:02:47Z","source":"NASA Breaking","category":"space_activity"},{"title":"I Am Artemis: Kathleen Harmon","link":"https://www.nasa.gov/missions/artemis/i-am-artemis/i-am-artemis-kathleen-harmon/","published_at":"2026-05-12T14:40:56Z","source":"NASA Breaking","category":"space_activity"},{"title":"Australia’s Cloudy Beauty","link":"https://science.nasa.gov/earth/earth-observatory/australias-cloudy-beauty/","published_at":"2026-05-12T04:01:00Z","source":"NASA Breaking","category":"space_activity"},{"title":"Curiosity Blog, Sols 4886-4892: Ingenuity and Perseverance, Curiosity Style","link":"https://science.nasa.gov/blog/curiosity-blog-sols-4886-4892-ingenuity-and-perseverance-curiosity-style/","published_at":"2026-05-12T01:38:30Z","source":"NASA Breaking","category":"space_activity"},{"title":"Solar flare M1.6 at N15W60","link":"https://www.swpc.noaa.gov/products/solar-and-geophysical-event-reports","published_at":""},{"title":"CME detected speed 382.0 km/s","link":"https://ccmc.gsfc.nasa.gov/donki/","published_at":""}]}